README
setup.py
vipr_data.egg-info/PKG-INFO
vipr_data.egg-info/SOURCES.txt
vipr_data.egg-info/dependency_links.txt
vipr_data.egg-info/requires.txt
vipr_data.egg-info/top_level.txt
viprdata/__init__.py
viprdata/viprdata.py