Metadata-Version: 1.0
Name: vipr-data
Version: 0.4.1
Summary: EMC ViPR Data Services SDK for Python
Home-page: https://community.emc.com/community/edn/vipr-data-services
Author: EMC
Author-email: ViPR.Data.Services.SDK@emc.com
License: BSD
Keywords: emc vipr dataservices sdk
Platform: UNKNOWN
Classifier: Development Status :: 4 - Beta
Classifier: Topic :: Utilities
Classifier: License :: OSI Approved :: BSD License
